pydetection/__init__.py
pydetection-0.0.4.dist-info/LICENCE
pydetection-0.0.4.dist-info/METADATA
pydetection-0.0.4.dist-info/WHEEL
pydetection-0.0.4.dist-info/top_level.txt
pydetection-0.0.4.dist-info/RECORD
