Metadata-Version: 2.1
Name: pydetection
Version: 0.0.4
Summary: This package will allow users to detect objects, such as hands and fingers, in a very simple way.
Home-page: https://github.com/Ayaan-Imran/pydetection
Author: Ayaan Imran
Author-email: miskiacuberayaan2509@gmail.com
Classifier: Programming Language :: Python
Classifier: License :: OSI Approved :: MIT License
Classifier: Operating System :: OS Independent
Requires-Python: <=3.7
License-File: LICENCE
